[
  {
    "id": 1,
    "title": "Naranja",
    "description": "Descripción de la naranja",
    "price": 90,
    "status": true,
    "code": "ABC123",
    "stock": 55,
    "category": "fruta",
    "thumbnails": [
      "Ruta de imagen"
    ]
  },
  {
    "id": 3,
    "title": "Banana",
    "description": "Descripción de la banana",
    "price": 70,
    "status": true,
    "code": "BCA231",
    "stock": 40,
    "category": "fruta",
    "thumbnails": [
      "Ruta de imagen"
    ]
  },
  {
    "id": 4,
    "title": "Sandía",
    "description": "Descripción de la sandía",
    "price": 900,
    "status": true,
    "code": "DFG543",
    "stock": 20,
    "category": "fruta",
    "thumbnails": [
      "Ruta de imagen"
    ]
  },
  {
    "id": 5,
    "title": "Uvas",
    "description": "Descripción de las uvas",
    "price": 700,
    "status": true,
    "code": "JHG324",
    "stock": 50,
    "category": "fruta",
    "thumbnails": [
      "Ruta de imagen"
    ]
  },
  {
    "id": 6,
    "title": "Ciruela",
    "description": "Descripción de las ciruela",
    "price": 200,
    "status": true,
    "code": "KML123",
    "stock": 80,
    "category": "fruta",
    "thumbnails": [
      "Ruta de imagen"
    ]
  },
  {
    "id": 7,
    "title": "Mandarina",
    "description": "Descripción de la mandarina",
    "price": 130,
    "status": true,
    "code": "LNM321",
    "stock": 70,
    "category": "fruta",
    "thumbnails": [
      "Ruta de imagen"
    ]
  },
  {
    "id": 8,
    "title": "Kiwi",
    "description": "Descripción del kiwi",
    "price": 350,
    "status": true,
    "code": "ABC987",
    "stock": 35,
    "category": "fruta",
    "thumbnails": [
      "Ruta de imagen"
    ]
  },
  {
    "id": 9,
    "title": "Cebolla",
    "description": "Descripción de la cebolla",
    "price": 80,
    "status": true,
    "code": "DCA543",
    "stock": 110,
    "category": "verdura",
    "thumbnails": [
      "Ruta de imagen"
    ]
  },
  {
    "id": 10,
    "title": "Zuccini",
    "description": "Descripción del zuccini",
    "price": 119,
    "status": true,
    "code": "MBK352",
    "stock": 99,
    "category": "verdura",
    "thumbnails": [
      "URL de la imagen 1",
      "URL de la imagen 2"
    ]
  },
  {
    "id": 11,
    "title": "Pepino",
    "description": "Descripción del pepino",
    "code": "MNS124",
    "price": 89,
    "status": true,
    "stock": 100,
    "category": "verdura",
    "thumbnails": [
      "URL de la imagen 1",
      "URL de la imagen 2"
    ]
  }
]